pyps4_2ndscreen/__init__.py
pyps4_2ndscreen/__main__.py
pyps4_2ndscreen/__version__.py
pyps4_2ndscreen/connection.py
pyps4_2ndscreen/credential.py
pyps4_2ndscreen/ddp.py
pyps4_2ndscreen/errors.py
pyps4_2ndscreen/helpers.py
pyps4_2ndscreen/media_art.py
pyps4_2ndscreen/oauth.py
pyps4_2ndscreen/ps4.py
pyps4_2ndscreen-1.3.1.dist-info/LICENSE
pyps4_2ndscreen-1.3.1.dist-info/METADATA
pyps4_2ndscreen-1.3.1.dist-info/WHEEL
pyps4_2ndscreen-1.3.1.dist-info/entry_points.txt
pyps4_2ndscreen-1.3.1.dist-info/top_level.txt
pyps4_2ndscreen-1.3.1.dist-info/RECORD
