Metadata-Version: 2.1
Name: pyps4_2ndscreen
Version: 1.3.1
Summary: PS4 2nd Screen Python Library
Home-page: https://github.com/ktnrg45/pyps4-2ndscreen
Author: ktnrg45
Author-email: ktnrg45dev@gmail.com
License: LGPLv2+
Keywords: playstation sony ps4 2nd screen 2ndscreen
Platform: UNKNOWN
Classifier: Development Status :: 5 - Production/Stable
Classifier: Environment :: Console
Classifier: Environment :: Console :: Curses
Classifier: Framework :: AsyncIO
Classifier: License :: OSI Approved :: GNU Lesser General Public License v2 or later (LGPLv2+)
Classifier: Natural Language :: English
Classifier: Operating System :: OS Independent
Classifier: Programming Language :: Python :: 3.6
Classifier: Programming Language :: Python :: 3.7
Classifier: Programming Language :: Python :: 3.8
Classifier: Topic :: Games/Entertainment
Classifier: Topic :: Home Automation
Classifier: Topic :: Software Development :: Libraries :: Python Modules
Classifier: Topic :: System :: Hardware
Requires-Python: >=3.6.0
